loadept_mcp_filesystem/__init__.py
loadept_mcp_filesystem/__main__.py
loadept_mcp_filesystem/server.py
loadept_mcp_filesystem/schemas/__init__.py
loadept_mcp_filesystem/schemas/tool_schema.py
loadept_mcp_filesystem/tools/__init__.py
loadept_mcp_filesystem/tools/tools.py
loadept_mcp_filesystem/utils/__init__.py
loadept_mcp_filesystem/utils/decorators.py
loadept_mcp_filesystem/utils/errors.py
loadept_mcp_filesystem/utils/globals.py
loadept_mcp_filesystem-0.3.3.dist-info/METADATA
loadept_mcp_filesystem-0.3.3.dist-info/WHEEL
loadept_mcp_filesystem-0.3.3.dist-info/entry_points.txt
loadept_mcp_filesystem-0.3.3.dist-info/RECORD
