Metadata-Version: 2.4
Name: loadept-mcp-filesystem
Version: 0.3.3
Summary: MCP Server for Filesystem Operations
Author: loadept
Maintainer-email: loadept <loadept3@gmail.com>
Keywords: automation,filesystem,llm,mcp
Requires-Python: >=3.13
Requires-Dist: mcp>=1.13.0
Requires-Dist: openpyxl>=3.1.5
Requires-Dist: pandas>=2.3.2
Requires-Dist: pydantic>=2.11.7
